visier/__init__.py
visier/sdk/__init__.py
visier/sdk/api/__init__.py
visier/sdk/api/data_version_export/__init__.py
visier/sdk/api/data_version_export/api_client.py
visier/sdk/api/data_version_export/api_response.py
visier/sdk/api/data_version_export/configuration.py
visier/sdk/api/data_version_export/exceptions.py
visier/sdk/api/data_version_export/py.typed
visier/sdk/api/data_version_export/rest.py
visier/sdk/api/data_version_export/api/__init__.py
visier/sdk/api/data_version_export/api/data_version_export_v1_alpha_api.py
visier/sdk/api/data_version_export/models/__init__.py
visier/sdk/api/data_version_export/models/data_version_export_column_dto.py
visier/sdk/api/data_version_export/models/data_version_export_data_version_summary_dto.py
visier/sdk/api/data_version_export/models/data_version_export_data_versions_dto.py
visier/sdk/api/data_version_export/models/data_version_export_dto.py
visier/sdk/api/data_version_export/models/data_version_export_file_dto.py
visier/sdk/api/data_version_export/models/data_version_export_job_status_dto.py
visier/sdk/api/data_version_export/models/data_version_export_part_file_dto.py
visier/sdk/api/data_version_export/models/data_version_export_schedule_job_request_dto.py
visier/sdk/api/data_version_export/models/data_version_export_schedule_job_response_dto.py
visier/sdk/api/data_version_export/models/data_version_export_table_dto.py
visier/sdk/api/data_version_export/models/data_version_exports_dto.py
visier/sdk/api/data_version_export/models/google_protobuf_any.py
visier/sdk/api/data_version_export/models/status.py
visier.sdk.api.data_version_export-0.0.5.dist-info/METADATA
visier.sdk.api.data_version_export-0.0.5.dist-info/WHEEL
visier.sdk.api.data_version_export-0.0.5.dist-info/top_level.txt
visier.sdk.api.data_version_export-0.0.5.dist-info/RECORD
